betfairdatabase/__init__.py
betfairdatabase/__main__.py
betfairdatabase/api.py
betfairdatabase/cli.py
betfairdatabase/const.py
betfairdatabase/database.py
betfairdatabase/exceptions.py
betfairdatabase/imports.py
betfairdatabase/market.py
betfairdatabase/marketdef.py
betfairdatabase/metadata.py
betfairdatabase/racing.py
betfairdatabase/utils.py
betfairdatabase-1.3.1.dist-info/LICENSE
betfairdatabase-1.3.1.dist-info/METADATA
betfairdatabase-1.3.1.dist-info/WHEEL
betfairdatabase-1.3.1.dist-info/entry_points.txt
betfairdatabase-1.3.1.dist-info/top_level.txt
betfairdatabase-1.3.1.dist-info/RECORD
