Metadata-Version: 2.2
Name: betfairdatabase
Version: 1.3.1
Summary: Turns a collection of historical Betfair data into a queryable SQL database.
Author-email: Mario Zaja <mzaja0@gmail.com>
License: MIT License
Project-URL: Homepage, https://github.com/mzaja/betfair-database
Project-URL: Bug Tracker, https://github.com/mzaja/betfair-database/issues
Keywords: betfair,trading,betting,database
Classifier: Programming Language :: Python :: 3.10
Classifier: Programming Language :: Python :: 3.11
Classifier: Programming Language :: Python :: 3.12
Classifier: Programming Language :: Python :: 3.13
Classifier: License :: OSI Approved :: MIT License
Classifier: Operating System :: OS Independent
Requires-Python: >=3.10
License-File: LICENSE
Requires-Dist: tqdm>=4.1.0
